README.rst
requirements.txt
setup.py
lapti/__init__.py
lapti/flask_utils.py
lapti/peewee_utils.py
lapti.egg-info/PKG-INFO
lapti.egg-info/SOURCES.txt
lapti.egg-info/dependency_links.txt
lapti.egg-info/requires.txt
lapti.egg-info/top_level.txt